<?xml version="1.0" encoding="UTF-8"?>

<FLOW VERSION="3.0" CLEANUP="true">
  <COMMENT>Initialize</COMMENT>

  <!-- nodes -->

<MAP TIMEOUT="" MODE="STANDALONE">
  <COMMENT>Initialize</COMMENT>
  <MAPTARGET>

<Values version="2.0">
  <record name="xml" javaclass="com.wm.util.Values">
    <value name="node_type">record</value>
    <value name="node_subtype">unknown</value>
    <value name="is_public">false</value>
    <value name="field_type">record</value>
    <value name="field_dim">0</value>
    <value name="wrapper_type">IData</value>
    <value name="nillable">true</value>
    <value name="form_qualified">false</value>
    <value name="is_global">false</value>
    <array name="rec_fields" type="record" depth="1">
      <record javaclass="com.wm.util.Values">
        <value name="node_type">record</value>
        <value name="node_subtype">unknown</value>
        <value name="node_comment"></value>
        <record name="node_hints" javaclass="com.wm.util.Values">
          <value name="field_largerEditor">false</value>
          <value name="field_password">false</value>
        </record>
        <value name="is_public">false</value>
        <value name="field_name">amsCanonicals:CustomerOrder</value>
        <value name="field_type">recref</value>
        <value name="field_dim">0</value>
        <value name="wrapper_type">IData</value>
        <value name="nillable">true</value>
        <value name="form_qualified">false</value>
        <value name="is_global">false</value>
        <value name="rec_closed">true</value>
        <value name="modifiable">true</value>
        <value name="rec_ref">amsCanonicals:CustomerOrder</value>
      </record>
      <record javaclass="com.wm.util.Values">
        <value name="node_type">record</value>
        <value name="node_subtype">unknown</value>
        <value name="is_public">false</value>
        <value name="field_name">SQL</value>
        <value name="field_type">record</value>
        <value name="field_dim">0</value>
        <value name="wrapper_type">IData</value>
        <value name="nillable">true</value>
        <value name="form_qualified">false</value>
        <value name="is_global">false</value>
        <array name="rec_fields" type="record" depth="1">
          <record javaclass="com.wm.util.Values">
            <value name="node_type">unknown</value>
            <value name="node_subtype">unknown</value>
            <value name="is_public">false</value>
            <value name="field_name">update</value>
            <value name="field_type">string</value>
            <value name="field_dim">0</value>
            <value name="nillable">true</value>
            <value name="form_qualified">false</value>
            <value name="is_global">false</value>
          </record>
        </array>
        <value name="modifiable">true</value>
      </record>
      <record javaclass="com.wm.util.Values">
        <value name="node_type">unknown</value>
        <value name="node_subtype">unknown</value>
        <value name="is_public">false</value>
        <value name="field_name">server</value>
        <value name="field_type">string</value>
        <value name="field_dim">0</value>
        <value name="nillable">true</value>
        <value name="form_qualified">false</value>
        <value name="is_global">false</value>
      </record>
    </array>
    <value name="modifiable">true</value>
  </record>
</Values>
</MAPTARGET>
  <MAPSOURCE>

<Values version="2.0">
  <record name="xml" javaclass="com.wm.util.Values">
    <value name="node_type">record</value>
    <value name="node_subtype">unknown</value>
    <value name="is_public">false</value>
    <value name="field_type">record</value>
    <value name="field_dim">0</value>
    <value name="wrapper_type">IData</value>
    <value name="nillable">true</value>
    <value name="form_qualified">false</value>
    <value name="is_global">false</value>
    <array name="rec_fields" type="record" depth="1">
    </array>
    <value name="modifiable">true</value>
  </record>
</Values>
</MAPSOURCE>

  <!-- nodes -->

<MAPSET NAME="Setter" OVERWRITE="true" VARIABLES="false" GLOBALVARIABLES="false" FIELD="/SQL;2;0/update;1;0">
  <DATA ENCODING="XMLValues" I18N="true">

<Values version="2.0">
  <value name="xml">a2a.ping_cn.update_cn_entry</value>
  <record name="type" javaclass="com.wm.util.Values">
    <value name="node_type">record</value>
    <value name="node_subtype">unknown</value>
    <value name="is_public">false</value>
    <value name="field_name">update</value>
    <value name="field_type">string</value>
    <value name="field_dim">0</value>
    <value name="nillable">true</value>
    <value name="form_qualified">false</value>
    <value name="is_global">false</value>
  </record>
</Values>
</DATA>
</MAPSET>

<MAPINVOKE SERVICE="amsUMPing.util:getInstance" VALIDATE-IN="$none" VALIDATE-OUT="$none" INVOKE-ORDER="0">

  <!-- nodes -->

<MAP MODE="INVOKEINPUT">
</MAP>

<MAP MODE="INVOKEOUTPUT">

  <!-- nodes -->

<MAPCOPY FROM="/instance;1;0" TO="/server;1;0">
</MAPCOPY>
</MAP>
</MAPINVOKE>
</MAP>

<INVOKE TIMEOUT="" SERVICE="amsDB.db:executeStoreProcedureAMSDB" VALIDATE-IN="$none" VALIDATE-OUT="$none">
  <COMMENT>Update Log</COMMENT>

  <!-- nodes -->

<MAP MODE="INPUT">
  <MAPTARGET>

<Values version="2.0">
  <record name="xml" javaclass="com.wm.util.Values">
    <value name="node_type">record</value>
    <value name="node_subtype">unknown</value>
    <value name="is_public">false</value>
    <value name="field_type">record</value>
    <value name="field_dim">0</value>
    <value name="wrapper_type">IData</value>
    <value name="nillable">true</value>
    <value name="form_qualified">false</value>
    <value name="is_global">false</value>
    <array name="rec_fields" type="record" depth="1">
      <record javaclass="com.wm.util.Values">
        <value name="node_type">unknown</value>
        <value name="node_subtype">unknown</value>
        <value name="node_comment"></value>
        <record name="node_hints" javaclass="com.wm.util.Values">
          <null name="field_usereditable"/>
          <value name="field_largerEditor">false</value>
          <value name="field_password">false</value>
        </record>
        <value name="is_public">false</value>
        <value name="field_name">storeProcedure</value>
        <value name="field_type">string</value>
        <value name="field_dim">0</value>
        <value name="nillable">false</value>
        <value name="form_qualified">false</value>
        <value name="is_global">false</value>
      </record>
      <record javaclass="com.wm.util.Values">
        <value name="node_type">record</value>
        <value name="node_subtype">unknown</value>
        <value name="node_comment"></value>
        <record name="node_hints" javaclass="com.wm.util.Values">
          <null name="field_usereditable"/>
          <value name="field_largerEditor">false</value>
          <value name="field_password">false</value>
        </record>
        <value name="is_public">false</value>
        <value name="field_name">dbURL</value>
        <value name="field_type">string</value>
        <value name="field_dim">0</value>
        <value name="nillable">false</value>
        <value name="form_qualified">false</value>
        <value name="is_global">false</value>
      </record>
      <record javaclass="com.wm.util.Values">
        <value name="node_type">record</value>
        <value name="node_subtype">unknown</value>
        <value name="node_comment"></value>
        <record name="node_hints" javaclass="com.wm.util.Values">
          <null name="field_usereditable"/>
          <value name="field_largerEditor">false</value>
          <value name="field_password">false</value>
        </record>
        <value name="is_public">false</value>
        <value name="field_name">service</value>
        <value name="field_type">string</value>
        <value name="field_dim">0</value>
        <value name="field_opt">true</value>
        <value name="nillable">true</value>
        <value name="form_qualified">false</value>
        <value name="is_global">false</value>
      </record>
      <record javaclass="com.wm.util.Values">
        <value name="node_type">record</value>
        <value name="node_subtype">unknown</value>
        <value name="node_comment"></value>
        <record name="node_hints" javaclass="com.wm.util.Values">
          <value name="field_largerEditor">false</value>
          <value name="field_password">false</value>
        </record>
        <value name="is_public">false</value>
        <value name="field_name">parameters</value>
        <value name="field_type">string</value>
        <value name="field_dim">1</value>
        <value name="field_opt">true</value>
        <value name="nillable">true</value>
        <value name="form_qualified">false</value>
        <value name="is_global">false</value>
        <value name="is_soap_array_encoding_used">true</value>
      </record>
      <record javaclass="com.wm.util.Values">
        <value name="node_type">record</value>
        <value name="node_subtype">unknown</value>
        <value name="node_comment"></value>
        <record name="node_hints" javaclass="com.wm.util.Values">
          <value name="field_largerEditor">false</value>
          <value name="field_password">false</value>
        </record>
        <value name="is_public">false</value>
        <value name="field_name">outputParamsList</value>
        <value name="field_type">string</value>
        <value name="field_dim">1</value>
        <value name="field_opt">true</value>
        <value name="nillable">true</value>
        <value name="form_qualified">false</value>
        <value name="is_global">false</value>
        <value name="is_soap_array_encoding_used">true</value>
      </record>
      <record javaclass="com.wm.util.Values">
        <value name="node_type">record</value>
        <value name="node_subtype">unknown</value>
        <value name="node_comment"></value>
        <record name="node_hints" javaclass="com.wm.util.Values">
          <value name="field_largerEditor">false</value>
          <value name="field_password">false</value>
        </record>
        <value name="is_public">false</value>
        <value name="field_name">inputParamsDoc</value>
        <value name="field_type">record</value>
        <value name="field_dim">0</value>
        <value name="field_opt">true</value>
        <value name="wrapper_type">IData</value>
        <value name="nillable">true</value>
        <value name="form_qualified">false</value>
        <value name="is_global">false</value>
        <array name="rec_fields" type="record" depth="1">
        </array>
        <value name="modifiable">true</value>
      </record>
      <record javaclass="com.wm.util.Values">
        <value name="node_type">record</value>
        <value name="node_subtype">unknown</value>
        <value name="node_comment"></value>
        <record name="node_hints" javaclass="com.wm.util.Values">
          <value name="field_largerEditor">false</value>
          <value name="field_password">false</value>
        </record>
        <value name="is_public">false</value>
        <value name="field_name">outputParamsDoc</value>
        <value name="field_type">record</value>
        <value name="field_dim">0</value>
        <value name="field_opt">true</value>
        <value name="wrapper_type">IData</value>
        <value name="nillable">true</value>
        <value name="form_qualified">false</value>
        <value name="is_global">false</value>
        <array name="rec_fields" type="record" depth="1">
        </array>
        <value name="modifiable">true</value>
      </record>
    </array>
    <value name="modifiable">true</value>
  </record>
</Values>
</MAPTARGET>
  <MAPSOURCE>

<Values version="2.0">
  <record name="xml" javaclass="com.wm.util.Values">
    <value name="node_type">record</value>
    <value name="node_subtype">unknown</value>
    <value name="is_public">false</value>
    <value name="field_type">record</value>
    <value name="field_dim">0</value>
    <value name="wrapper_type">IData</value>
    <value name="nillable">true</value>
    <value name="form_qualified">false</value>
    <value name="is_global">false</value>
    <array name="rec_fields" type="record" depth="1">
      <record javaclass="com.wm.util.Values">
        <value name="node_type">record</value>
        <value name="node_subtype">unknown</value>
        <value name="node_comment"></value>
        <record name="node_hints" javaclass="com.wm.util.Values">
          <value name="field_largerEditor">false</value>
          <value name="field_password">false</value>
        </record>
        <value name="is_public">false</value>
        <value name="field_name">amsCanonicals:CustomerOrder</value>
        <value name="field_type">recref</value>
        <value name="field_dim">0</value>
        <value name="wrapper_type">IData</value>
        <value name="nillable">true</value>
        <value name="form_qualified">false</value>
        <value name="is_global">false</value>
        <value name="rec_closed">true</value>
        <value name="modifiable">true</value>
        <value name="rec_ref">amsCanonicals:CustomerOrder</value>
      </record>
      <record javaclass="com.wm.util.Values">
        <value name="node_type">record</value>
        <value name="node_subtype">unknown</value>
        <value name="is_public">false</value>
        <value name="field_name">SQL</value>
        <value name="field_type">record</value>
        <value name="field_dim">0</value>
        <value name="wrapper_type">IData</value>
        <value name="nillable">true</value>
        <value name="form_qualified">false</value>
        <value name="is_global">false</value>
        <array name="rec_fields" type="record" depth="1">
          <record javaclass="com.wm.util.Values">
            <value name="node_type">unknown</value>
            <value name="node_subtype">unknown</value>
            <value name="is_public">false</value>
            <value name="field_name">update</value>
            <value name="field_type">string</value>
            <value name="field_dim">0</value>
            <value name="nillable">true</value>
            <value name="form_qualified">false</value>
            <value name="is_global">false</value>
          </record>
        </array>
        <value name="modifiable">true</value>
      </record>
      <record javaclass="com.wm.util.Values">
        <value name="node_type">unknown</value>
        <value name="node_subtype">unknown</value>
        <value name="is_public">false</value>
        <value name="field_name">server</value>
        <value name="field_type">string</value>
        <value name="field_dim">0</value>
        <value name="nillable">true</value>
        <value name="form_qualified">false</value>
        <value name="is_global">false</value>
      </record>
    </array>
    <value name="modifiable">true</value>
  </record>
</Values>
</MAPSOURCE>

  <!-- nodes -->

<MAPCOPY FROM="/SQL;2;0/update;1;0" TO="/storeProcedure;1;0">
</MAPCOPY>

<MAPCOPY FROM="/amsCanonicals:CustomerOrder;4;0;amsCanonicals:CustomerOrder/ApplicationArea;4;0;amsCanonicals.doc:ApplicationArea/UserArea;2;0/dbAlias;1;0" TO="/dbURL;1;0">
</MAPCOPY>

<MAPCOPY FROM="/amsCanonicals:CustomerOrder;4;0;amsCanonicals:CustomerOrder/ApplicationArea;4;0;amsCanonicals.doc:ApplicationArea/DocumentID;1;0" TO="/parameters[0];1;1">
</MAPCOPY>

<MAPCOPY FROM="/server;1;0" TO="/parameters[1];1;1">
</MAPCOPY>

<MAPSET NAME="Setter" OVERWRITE="true" VARIABLES="false" GLOBALVARIABLES="false" FIELD="/service;1;0">
  <DATA ENCODING="XMLValues" I18N="true">

<Values version="2.0">
  <value name="xml">amsUMPing.process:logCNReceipt</value>
  <record name="type" javaclass="com.wm.util.Values">
    <value name="node_type">record</value>
    <value name="node_subtype">unknown</value>
    <value name="node_comment"></value>
    <record name="node_hints" javaclass="com.wm.util.Values">
      <null name="field_usereditable"/>
      <value name="field_largerEditor">false</value>
      <value name="field_password">false</value>
    </record>
    <value name="is_public">false</value>
    <value name="field_name">service</value>
    <value name="field_type">string</value>
    <value name="field_dim">0</value>
    <value name="field_opt">true</value>
    <value name="nillable">true</value>
    <value name="form_qualified">false</value>
    <value name="is_global">false</value>
  </record>
</Values>
</DATA>
</MAPSET>
</MAP>

<MAP MODE="OUTPUT">
  <MAPTARGET>

<Values version="2.0">
  <record name="xml" javaclass="com.wm.util.Values">
    <value name="node_type">record</value>
    <value name="node_subtype">unknown</value>
    <value name="is_public">false</value>
    <value name="field_type">record</value>
    <value name="field_dim">0</value>
    <value name="wrapper_type">IData</value>
    <value name="nillable">true</value>
    <value name="form_qualified">false</value>
    <value name="is_global">false</value>
    <array name="rec_fields" type="record" depth="1">
      <record javaclass="com.wm.util.Values">
        <value name="node_type">unknown</value>
        <value name="node_subtype">unknown</value>
        <value name="is_public">false</value>
        <value name="field_name">storeProcedure</value>
        <value name="field_type">string</value>
        <value name="field_dim">0</value>
        <value name="nillable">true</value>
        <value name="form_qualified">false</value>
        <value name="is_global">false</value>
      </record>
      <record javaclass="com.wm.util.Values">
        <value name="node_type">unknown</value>
        <value name="node_subtype">unknown</value>
        <value name="is_public">false</value>
        <value name="field_name">dbURL</value>
        <value name="field_type">string</value>
        <value name="field_dim">0</value>
        <value name="nillable">true</value>
        <value name="form_qualified">false</value>
        <value name="is_global">false</value>
      </record>
      <record javaclass="com.wm.util.Values">
        <value name="node_type">record</value>
        <value name="node_subtype">unknown</value>
        <value name="node_comment"></value>
        <record name="node_hints" javaclass="com.wm.util.Values">
          <value name="field_largerEditor">false</value>
          <value name="field_password">false</value>
        </record>
        <value name="is_public">false</value>
        <value name="field_name">amsCanonicals:CustomerOrder</value>
        <value name="field_type">recref</value>
        <value name="field_dim">0</value>
        <value name="wrapper_type">IData</value>
        <value name="nillable">true</value>
        <value name="form_qualified">false</value>
        <value name="is_global">false</value>
        <value name="rec_closed">true</value>
        <value name="modifiable">true</value>
        <value name="rec_ref">amsCanonicals:CustomerOrder</value>
      </record>
      <record javaclass="com.wm.util.Values">
        <value name="node_type">unknown</value>
        <value name="node_subtype">unknown</value>
        <value name="is_public">false</value>
        <value name="field_name">parameters</value>
        <value name="field_type">string</value>
        <value name="field_dim">1</value>
        <value name="nillable">true</value>
        <value name="form_qualified">false</value>
        <value name="is_global">false</value>
        <value name="is_soap_array_encoding_used">false</value>
      </record>
      <record javaclass="com.wm.util.Values">
        <value name="node_type">record</value>
        <value name="node_subtype">unknown</value>
        <value name="is_public">false</value>
        <value name="field_name">SQL</value>
        <value name="field_type">record</value>
        <value name="field_dim">0</value>
        <value name="wrapper_type">IData</value>
        <value name="nillable">true</value>
        <value name="form_qualified">false</value>
        <value name="is_global">false</value>
        <array name="rec_fields" type="record" depth="1">
          <record javaclass="com.wm.util.Values">
            <value name="node_type">unknown</value>
            <value name="node_subtype">unknown</value>
            <value name="is_public">false</value>
            <value name="field_name">update</value>
            <value name="field_type">string</value>
            <value name="field_dim">0</value>
            <value name="nillable">true</value>
            <value name="form_qualified">false</value>
            <value name="is_global">false</value>
          </record>
        </array>
        <value name="modifiable">true</value>
      </record>
      <record javaclass="com.wm.util.Values">
        <value name="node_type">unknown</value>
        <value name="node_subtype">unknown</value>
        <value name="is_public">false</value>
        <value name="field_name">server</value>
        <value name="field_type">string</value>
        <value name="field_dim">0</value>
        <value name="nillable">true</value>
        <value name="form_qualified">false</value>
        <value name="is_global">false</value>
      </record>
      <record javaclass="com.wm.util.Values">
        <value name="node_type">record</value>
        <value name="node_subtype">unknown</value>
        <value name="node_comment"></value>
        <record name="node_hints" javaclass="com.wm.util.Values">
          <value name="field_largerEditor">false</value>
          <value name="field_password">false</value>
        </record>
        <value name="is_public">false</value>
        <value name="field_name">resultsList</value>
        <value name="field_type">string</value>
        <value name="field_dim">1</value>
        <value name="field_opt">true</value>
        <value name="nillable">true</value>
        <value name="form_qualified">false</value>
        <value name="is_global">false</value>
        <value name="is_soap_array_encoding_used">false</value>
      </record>
      <record javaclass="com.wm.util.Values">
        <value name="node_type">record</value>
        <value name="node_subtype">unknown</value>
        <value name="node_comment"></value>
        <record name="node_hints" javaclass="com.wm.util.Values">
          <value name="field_largerEditor">false</value>
          <value name="field_password">false</value>
        </record>
        <value name="is_public">false</value>
        <value name="field_name">resultSetsList</value>
        <value name="field_type">record</value>
        <value name="field_dim">1</value>
        <value name="field_opt">true</value>
        <value name="wrapper_type">IData</value>
        <value name="nillable">true</value>
        <value name="form_qualified">false</value>
        <value name="is_global">false</value>
        <value name="is_soap_array_encoding_used">false</value>
        <array name="rec_fields" type="record" depth="1">
        </array>
        <value name="rec_closed">true</value>
        <value name="modifiable">true</value>
      </record>
      <record javaclass="com.wm.util.Values">
        <value name="node_type">record</value>
        <value name="node_subtype">unknown</value>
        <value name="node_comment"></value>
        <record name="node_hints" javaclass="com.wm.util.Values">
          <value name="field_largerEditor">false</value>
          <value name="field_password">false</value>
        </record>
        <value name="is_public">false</value>
        <value name="field_name">resultsDoc</value>
        <value name="field_type">record</value>
        <value name="field_dim">0</value>
        <value name="field_opt">true</value>
        <value name="wrapper_type">IData</value>
        <value name="nillable">true</value>
        <value name="form_qualified">false</value>
        <value name="is_global">false</value>
        <array name="rec_fields" type="record" depth="1">
        </array>
        <value name="rec_closed">true</value>
        <value name="modifiable">true</value>
      </record>
      <record javaclass="com.wm.util.Values">
        <value name="node_type">record</value>
        <value name="node_subtype">unknown</value>
        <value name="node_comment"></value>
        <record name="node_hints" javaclass="com.wm.util.Values">
          <value name="field_largerEditor">false</value>
          <value name="field_password">false</value>
        </record>
        <value name="is_public">false</value>
        <value name="field_name">resultSetsDoc</value>
        <value name="field_type">record</value>
        <value name="field_dim">0</value>
        <value name="field_opt">true</value>
        <value name="wrapper_type">IData</value>
        <value name="nillable">true</value>
        <value name="form_qualified">false</value>
        <value name="is_global">false</value>
        <array name="rec_fields" type="record" depth="1">
        </array>
        <value name="rec_closed">true</value>
        <value name="modifiable">true</value>
      </record>
    </array>
    <value name="modifiable">true</value>
  </record>
</Values>
</MAPTARGET>
  <MAPSOURCE>

<Values version="2.0">
  <record name="xml" javaclass="com.wm.util.Values">
    <value name="node_type">record</value>
    <value name="node_subtype">unknown</value>
    <value name="is_public">false</value>
    <value name="field_type">record</value>
    <value name="field_dim">0</value>
    <value name="wrapper_type">IData</value>
    <value name="nillable">true</value>
    <value name="form_qualified">false</value>
    <value name="is_global">false</value>
    <array name="rec_fields" type="record" depth="1">
      <record javaclass="com.wm.util.Values">
        <value name="node_type">record</value>
        <value name="node_subtype">unknown</value>
        <value name="node_comment"></value>
        <record name="node_hints" javaclass="com.wm.util.Values">
          <value name="field_largerEditor">false</value>
          <value name="field_password">false</value>
        </record>
        <value name="is_public">false</value>
        <value name="field_name">resultsList</value>
        <value name="field_type">string</value>
        <value name="field_dim">1</value>
        <value name="field_opt">true</value>
        <value name="nillable">true</value>
        <value name="form_qualified">false</value>
        <value name="is_global">false</value>
        <value name="is_soap_array_encoding_used">false</value>
      </record>
      <record javaclass="com.wm.util.Values">
        <value name="node_type">record</value>
        <value name="node_subtype">unknown</value>
        <value name="node_comment"></value>
        <record name="node_hints" javaclass="com.wm.util.Values">
          <value name="field_largerEditor">false</value>
          <value name="field_password">false</value>
        </record>
        <value name="is_public">false</value>
        <value name="field_name">resultSetsList</value>
        <value name="field_type">record</value>
        <value name="field_dim">1</value>
        <value name="field_opt">true</value>
        <value name="wrapper_type">IData</value>
        <value name="nillable">true</value>
        <value name="form_qualified">false</value>
        <value name="is_global">false</value>
        <value name="is_soap_array_encoding_used">false</value>
        <array name="rec_fields" type="record" depth="1">
        </array>
        <value name="rec_closed">true</value>
        <value name="modifiable">true</value>
      </record>
      <record javaclass="com.wm.util.Values">
        <value name="node_type">record</value>
        <value name="node_subtype">unknown</value>
        <value name="node_comment"></value>
        <record name="node_hints" javaclass="com.wm.util.Values">
          <value name="field_largerEditor">false</value>
          <value name="field_password">false</value>
        </record>
        <value name="is_public">false</value>
        <value name="field_name">resultsDoc</value>
        <value name="field_type">record</value>
        <value name="field_dim">0</value>
        <value name="field_opt">true</value>
        <value name="wrapper_type">IData</value>
        <value name="nillable">true</value>
        <value name="form_qualified">false</value>
        <value name="is_global">false</value>
        <array name="rec_fields" type="record" depth="1">
        </array>
        <value name="rec_closed">true</value>
        <value name="modifiable">true</value>
      </record>
      <record javaclass="com.wm.util.Values">
        <value name="node_type">record</value>
        <value name="node_subtype">unknown</value>
        <value name="node_comment"></value>
        <record name="node_hints" javaclass="com.wm.util.Values">
          <value name="field_largerEditor">false</value>
          <value name="field_password">false</value>
        </record>
        <value name="is_public">false</value>
        <value name="field_name">resultSetsDoc</value>
        <value name="field_type">record</value>
        <value name="field_dim">0</value>
        <value name="field_opt">true</value>
        <value name="wrapper_type">IData</value>
        <value name="nillable">true</value>
        <value name="form_qualified">false</value>
        <value name="is_global">false</value>
        <array name="rec_fields" type="record" depth="1">
        </array>
        <value name="rec_closed">true</value>
        <value name="modifiable">true</value>
      </record>
    </array>
    <value name="modifiable">true</value>
  </record>
</Values>
</MAPSOURCE>

  <!-- nodes -->

<MAPDELETE FIELD="/storeProcedure;1;0">
</MAPDELETE>

<MAPDELETE FIELD="/dbURL;1;0">
</MAPDELETE>

<MAPDELETE FIELD="/amsCanonicals:CustomerOrder;4;0;amsCanonicals:CustomerOrder">
</MAPDELETE>

<MAPDELETE FIELD="/parameters;1;1">
</MAPDELETE>

<MAPDELETE FIELD="/SQL;2;0">
</MAPDELETE>

<MAPDELETE FIELD="/server;1;0">
</MAPDELETE>

<MAPDELETE FIELD="/resultsList;1;1">
</MAPDELETE>

<MAPDELETE FIELD="/resultSetsList;2;1">
</MAPDELETE>

<MAPDELETE FIELD="/resultsDoc;2;0">
</MAPDELETE>

<MAPDELETE FIELD="/resultSetsDoc;2;0">
</MAPDELETE>
</MAP>
</INVOKE>
</FLOW>
